Metadata-Version: 2.1
Name: a-pandas-ex-inspect2df
Version: 0.10
Summary: Converts the output of some inspect functions to a DataFrame
Home-page: https://github.com/hansalemaos/a_pandas_ex_inspect2df
Author: Johannes Fischer
Author-email: aulasparticularesdealemaosp@gmail.com
License: MIT
Keywords: pandas,inspect
Classifier: Development Status :: 4 - Beta
Classifier: Programming Language :: Python :: 3 :: Only
Classifier: Programming Language :: Python :: 3.10
Classifier: Topic :: Software Development :: Libraries :: Python Modules
Classifier: Topic :: Utilities
License-File: LICENSE.rst
Requires-Dist: a-pandas-ex-apply-ignore-exceptions
Requires-Dist: pandas
